LICENSE
setup.py
sway_auto_floating/__init__.py
sway_auto_floating/auto_floating.py
sway_auto_floating/shared.py
sway_auto_floating/toggle_floating.py
sway_auto_floating.egg-info/PKG-INFO
sway_auto_floating.egg-info/SOURCES.txt
sway_auto_floating.egg-info/dependency_links.txt
sway_auto_floating.egg-info/entry_points.txt
sway_auto_floating.egg-info/requires.txt
sway_auto_floating.egg-info/top_level.txt